aircraft/__init__.py
aircraft/actor_engine.py
aircraft/aircraft.py
aircraft/engine_proxy.py
aircraft/model_desc.py
aircraft/platform_factory.py
aircraft_infer-0.1.1.dist-info/LICENCE
aircraft_infer-0.1.1.dist-info/METADATA
aircraft_infer-0.1.1.dist-info/WHEEL
aircraft_infer-0.1.1.dist-info/top_level.txt
aircraft_infer-0.1.1.dist-info/RECORD
